MANIFEST.in
README.rst
requirements.txt
setup.py
ctk_cli_indexer/__init__.py
ctk_cli_indexer/extractor.py
ctk_cli_indexer/indexer.py
ctk_cli_indexer/main.py
ctk_cli_indexer.egg-info/PKG-INFO
ctk_cli_indexer.egg-info/SOURCES.txt
ctk_cli_indexer.egg-info/dependency_links.txt
ctk_cli_indexer.egg-info/entry_points.txt
ctk_cli_indexer.egg-info/requires.txt
ctk_cli_indexer.egg-info/top_level.txt