Metadata-Version: 1.1
Name: ctk-cli-indexer
Version: 0.4
Summary: Python utilities for creating an ElasticSearch database containing information on available CLI modules
Home-page: https://github.com/commontk/ctk-cli-indexer
Author: Hans Meine, Jean-Christophe Fillion-Robin
Author-email: hans_meine@gmx.net, jchris.fillionr@kitware.com
License: Apache 2.0
Platform: UNKNOWN
Classifier: Development Status :: 4 - Beta
Classifier: Environment :: Web Environment
Classifier: License :: OSI Approved :: Apache Software License
Classifier: Operating System :: OS Independent
Classifier: Programming Language :: Python :: 2
